README.txt
setup.py
collective/__init__.py
collective.collage.easyslider.egg-info/PKG-INFO
collective.collage.easyslider.egg-info/SOURCES.txt
collective.collage.easyslider.egg-info/dependency_links.txt
collective.collage.easyslider.egg-info/entry_points.txt
collective.collage.easyslider.egg-info/namespace_packages.txt
collective.collage.easyslider.egg-info/not-zip-safe
collective.collage.easyslider.egg-info/requires.txt
collective.collage.easyslider.egg-info/top_level.txt
collective/collage/__init__.py
collective/collage/easyslider/README.txt
collective/collage/easyslider/__init__.py
collective/collage/easyslider/browser.txt
collective/collage/easyslider/config.py
collective/collage/easyslider/configure.zcml
collective/collage/easyslider/interfaces.py
collective/collage/easyslider/setuphandlers.py
collective/collage/easyslider/tests.py
collective/collage/easyslider/version.txt
collective/collage/easyslider/browser/__init__.py
collective/collage/easyslider/browser/configure.zcml
collective/collage/easyslider/browser/utils.py
collective/collage/easyslider/browser/viewlets.py
collective/collage/easyslider/browser/views.py
collective/collage/easyslider/browser/resources/styles.css
collective/collage/easyslider/browser/templates/easyslider.pt
collective/collage/easyslider/browser/templates/manage.pt
collective/collage/easyslider/profiles/default/browserlayer.xml
collective/collage/easyslider/profiles/default/collective.collage.easyslider_various.txt
collective/collage/easyslider/profiles/default/cssregistry.xml
collective/collage/easyslider/profiles/default/import_steps.xml
collective/collage/easyslider/profiles/default/jsregistry.xml
docs/AUTHORS.txt
docs/HISTORY.txt
docs/INSTALL.txt
docs/LICENSE.GPL
docs/LICENSE.txt