Metadata-Version: 1.0
Name: collective.collage.easyslider
Version: 1.0.1
Summary: Collage view for content slide.
Home-page: http://plone.org/products/collective.collage.easyslider
Author: Rcom
Author-email: info@rcom.com.ar
License: GPL
Platform: UNKNOWN
Classifier: Framework :: Plone
Classifier: Programming Language :: Python
